README.txt
eddie-agent
ez_setup.py
setup.cfg
setup.py
EDDIE_Tool.egg-info/PKG-INFO
EDDIE_Tool.egg-info/SOURCES.txt
EDDIE_Tool.egg-info/dependency_links.txt
EDDIE_Tool.egg-info/entry_points.txt
EDDIE_Tool.egg-info/not-zip-safe
EDDIE_Tool.egg-info/top_level.txt
config-sample/eddie.cf
config-sample/rules/cache.rules
config-sample/rules/common.rules
config-sample/rules/dns.rules
config-sample/rules/host.rules
config-sample/rules/message.rules
config-sample/rules/news.rules
config-sample/rules/rrd.rules
config-sample/rules/sys_linux.rules
config-sample/rules/sys_solaris.rules
config-sample/rules/win32_sample.rules
contrib/eddie_wrapper/eddie_wrapper
contrib/init.d/README.txt
contrib/init.d/eddie-agent-init.d_script_for_redhat
contrib/init.d/eddie-agent.SMF-manifest.xml
contrib/init.d/eddie_wrapper-init.d_script_for_redhat
contrib/init.d/eddie_wrapper-init.d_script_for_solaris
contrib/spread/elvinrrd_spread_send.py
contrib/spread/elvinrrd_spread_watch.py
contrib/vim/README
contrib/vim/eddie.vim
development/testing/full_test_darwin.rules
development/testing/full_test_openbsd.rules
development/testing/message.rules
doc/CHANGES.txt
doc/LICENSE.txt
doc/QUICKSTART.txt
doc/README
doc/README.OpenBSD.txt
doc/README.win32.txt
doc/changes_ver_029.txt
doc/dev_guide.txt
doc/manual.html
eddietool/__init__.py
eddietool/commands.py
eddietool/version.py
eddietool/arch/__init__.py
eddietool/arch/Darwin/__init__.py
eddietool/arch/Darwin/df.py
eddietool/arch/Darwin/netstat.py
eddietool/arch/Darwin/proc.py
eddietool/arch/Darwin/system.py
eddietool/arch/FreeBSD/__init__.py
eddietool/arch/FreeBSD/df.py
eddietool/arch/FreeBSD/netstat.py
eddietool/arch/FreeBSD/proc.py
eddietool/arch/FreeBSD/system.py
eddietool/arch/HP_UX/__init__.py
eddietool/arch/HP_UX/df.py
eddietool/arch/HP_UX/netstat.py
eddietool/arch/HP_UX/proc.py
eddietool/arch/HP_UX/system.py
eddietool/arch/Linux/__init__.py
eddietool/arch/Linux/df.py
eddietool/arch/Linux/diskdevice.py
eddietool/arch/Linux/netstat.py
eddietool/arch/Linux/proc.py
eddietool/arch/Linux/system.py
eddietool/arch/Linux/linux_diskio/__init__.py
eddietool/arch/Linux/linux_diskio/linux_diskio.py
eddietool/arch/Linux/linux_diskio/tests/proc_diskstats.txt
