Metadata-Version: 1.0
Name: EDDIE-Tool
Version: 0.37.3.1
Summary: The EDDIE Tool is a system and network monitoring, security, and performance analysis agent developed entirely in threaded Python. Its key features are portability, extendibility, and powerful configuration.
Home-page: http://eddie-tool.net/
Author: Chris Miles
Author-email: miles.chris@gmail.com
License: GPL
Download-URL: http://pypi.python.org/pypi/EDDIE-Tool
Platform: UNKNOWN
Classifier: Development Status :: 5 - Production/Stable
Classifier: Environment :: No Input/Output (Daemon)
Classifier: Intended Audience :: System Administrators
Classifier: License :: OSI Approved :: GNU General Public License (GPL)
Classifier: Operating System :: MacOS :: MacOS X
Classifier: Operating System :: Microsoft :: Windows
Classifier: Operating System :: POSIX :: BSD :: FreeBSD
Classifier: Operating System :: POSIX :: BSD :: OpenBSD
Classifier: Operating System :: POSIX :: HP-UX
Classifier: Operating System :: POSIX :: Linux
Classifier: Operating System :: POSIX :: SunOS/Solaris
Classifier: Programming Language :: Python
Classifier: Topic :: System :: Monitoring
Classifier: Topic :: System :: Networking :: Monitoring
Classifier: Topic :: System :: Systems Administration
